sqlite4/SQLite4.py
sqlite4/__init__.py
tests/__init__.py
tests/test_crud_class.py
tests/test_multithread.py
tests/test_singleton.py
SQLite4-0.1.0.dist-info/LICENSE
SQLite4-0.1.0.dist-info/METADATA
SQLite4-0.1.0.dist-info/WHEEL
SQLite4-0.1.0.dist-info/top_level.txt
SQLite4-0.1.0.dist-info/RECORD
